setup.py
gaius/__init__.py
gaius/cli.py
gaius/service.py
gaius.egg-info/PKG-INFO
gaius.egg-info/SOURCES.txt
gaius.egg-info/dependency_links.txt
gaius.egg-info/entry_points.txt
gaius.egg-info/requires.txt
gaius.egg-info/top_level.txt
gaius.egg-info/zip-safe
scripts/gaius