Metadata-Version: 1.0
Name: gaius
Version: 141.0
Summary: The deployment client that triggers Crassus to deploy artefacts
Home-page: https://github.com/ImmobilienScout24/gaius
Author: UNKNOWN
Author-email: UNKNOWN
License: Apache License 2.0
Platform: UNKNOWN
Classifier: Development Status :: 4 - Beta
Classifier: Environment :: Console
Classifier: Intended Audience :: Developers
Classifier: Intended Audience :: System Administrators
Classifier: License :: OSI Approved :: Apache Software License
Classifier: Programming Language :: Python
Classifier: Topic :: System :: Systems Administration
